openvisualizer/__init__.py
openvisualizer/__main__.py
openvisualizer/main.py
openvisualizer/utils.py
openvisualizer/bspemulator/__init__.py
openvisualizer/bspemulator/bspboard.py
openvisualizer/bspemulator/bspdebugpins.py
openvisualizer/bspemulator/bspeui64.py
openvisualizer/bspemulator/bspleds.py
openvisualizer/bspemulator/bspmodule.py
openvisualizer/bspemulator/bspradio.py
openvisualizer/bspemulator/bspsctimer.py
openvisualizer/bspemulator/bspuart.py
openvisualizer/bspemulator/hwcrystal.py
openvisualizer/bspemulator/hwmodule.py
openvisualizer/bspemulator/hwsupply.py
openvisualizer/bspemulator/vcdlogger.py
openvisualizer/client/__init__.py
openvisualizer/client/main.py
openvisualizer/client/utils.py
openvisualizer/client/view.py
openvisualizer/client/webserver.py
openvisualizer/client/plugins/__init__.py
openvisualizer/client/plugins/macstats.py
openvisualizer/client/plugins/motestatus.py
openvisualizer/client/plugins/msf.py
openvisualizer/client/plugins/neighbors.py
openvisualizer/client/plugins/pktqueue.py
openvisualizer/client/plugins/plugin.py
openvisualizer/client/plugins/schedule.py
openvisualizer/client/web_files/static/css/bootstrap.css
openvisualizer/client/web_files/static/css/bootstrap.min.css
openvisualizer/client/web_files/static/css/d3.css
openvisualizer/client/web_files/static/css/openvisualizer.css
openvisualizer/client/web_files/static/font-awesome/css/font-awesome.css
openvisualizer/client/web_files/static/font-awesome/css/font-awesome.min.css
openvisualizer/client/web_files/static/font-awesome/fonts/FontAwesome.otf
openvisualizer/client/web_files/static/font-awesome/fonts/fontawesome-webfont.eot
openvisualizer/client/web_files/static/font-awesome/fonts/fontawesome-webfont.svg
openvisualizer/client/web_files/static/font-awesome/fonts/fontawesome-webfont.ttf
openvisualizer/client/web_files/static/font-awesome/fonts/fontawesome-webfont.woff
openvisualizer/client/web_files/static/images/favicon.ico
openvisualizer-2.0.0.dist-info/LICENSE.md
openvisualizer-2.0.0.dist-info/METADATA
openvisualizer-2.0.0.dist-info/WHEEL
openvisualizer-2.0.0.dist-info/entry_points.txt
openvisualizer-2.0.0.dist-info/top_level.txt
openvisualizer-2.0.0.dist-info/RECORD
