Metadata-Version: 2.1
Name: openvisualizer
Version: 2.0.0
Summary: Wireless sensor network monitoring and visualization tool
Home-page: https://openwsn.atlassian.net/wiki/display/OW/OpenVisualizer
Author: Thomas Watteyne
Author-email: watteyne@eecs.berkeley.edu
License: BSD 3-Clause
Keywords: 6TiSCH,Internet of Things,6LoWPAN,802.15.4e,sensor,mote
Platform: platform-independent
Classifier: Development Status :: 3 - Alpha
Classifier: Intended Audience :: Developers
Classifier: License :: OSI Approved :: BSD License
Classifier: Operating System :: OS Independent
Classifier: Programming Language :: Python
Classifier: Programming Language :: Python :: 2.7
Classifier: Topic :: Communications
Classifier: Topic :: Home Automation
Classifier: Topic :: Internet
Classifier: Topic :: Software Development
Requires-Python: <=2.7.18
Requires-Dist: pyserial
Requires-Dist: PyDispatcher
Requires-Dist: bottle
Requires-Dist: Sphinx
Requires-Dist: intelhex
Requires-Dist: setuptools (<=44.1.1)
Requires-Dist: openwsn-coap (>=0.0.7)
Requires-Dist: pycryptodome
Requires-Dist: cbor
Requires-Dist: hkdf
Requires-Dist: paho-mqtt
Requires-Dist: coloredlogs
Requires-Dist: verboselogs
Requires-Dist: click
Requires-Dist: blessed
Requires-Dist: ipaddr
Requires-Dist: scapy
Requires-Dist: sshtunnel
Requires-Dist: iotlabcli
Requires-Dist: appdirs
Requires-Dist: pywin32 ; sys_platform == "win32"
Requires-Dist: colorama ; sys_platform == "win32"
